connect/utils/peewee/__init__.py
connect/utils/peewee/exceptions.py
connect/utils/peewee/mixins.py
connect/utils/peewee/models.py
connect/utils/peewee/utils.py
peewee_model_utils-1.0.0.dist-info/LICENSE
peewee_model_utils-1.0.0.dist-info/METADATA
peewee_model_utils-1.0.0.dist-info/WHEEL
peewee_model_utils-1.0.0.dist-info/RECORD
